hatch_pyinstaller/__init__.py
hatch_pyinstaller/builder.py
hatch_pyinstaller/hooks.py
hatch_pyinstaller-1.0.1.dist-info/METADATA
hatch_pyinstaller-1.0.1.dist-info/WHEEL
hatch_pyinstaller-1.0.1.dist-info/entry_points.txt
hatch_pyinstaller-1.0.1.dist-info/licenses/LICENCE.txt
hatch_pyinstaller-1.0.1.dist-info/RECORD
